tzlocal-stubs/METADATA.toml
tzlocal-stubs/__init__.pyi
tzlocal-stubs/utils.pyi
tzlocal-stubs/windows_tz.pyi
types_tzlocal-5.1.0.1.dist-info/METADATA
types_tzlocal-5.1.0.1.dist-info/WHEEL
types_tzlocal-5.1.0.1.dist-info/top_level.txt
types_tzlocal-5.1.0.1.dist-info/RECORD
